{
    "songs": [{
        "name": "Quante volte",
        "lyrics": "Quante cose son cambiate nella vita <span style='color: red; margin: 0'>DUM</span>\nQuante cose sono sempre così\nQuante volte ho pensato è finita\nPoi mi risvegliavo il lunedì\nQuante volte ho pensato nella vita\nVoglio fare quello che mi va\nPoi le cose mi sfuggivan tra le dita\nE arrivava la realtà\nQuante cose son passate ormai, eh\nQuante cose che non torneranno mai\nQuante volte ho pensato nella vita\nPosso fare anche senza di te\nPoi mi risvegliavo tutto sudato\nSenza capire perché\nQuante volte ho sbagliato, sì\nQuante volte è andata bene così\nQuante volte ho fatto finta di niente\nMa ho capito, sì\nQuante volte sono arrivati i guai\nAnche se ero già migliore ormai\nIo non voglio più vivere\nSolo per fare compagnia\nIo non voglio più ridere\nNon mi diverto più ed è colpa mia\nNon ho voglia di credere\nChe domani sarà\nSarà diverso e poi chi lo sa?\nQuante volte ho pensato nella vita\nPosso fare anche senza di te\nPoi mi risvegliavo tutto sudato\nSenza vita che è\nQuante volte ho sbagliato sì\nQuante volte è andata bene così, eeh\nQuante volte ho fatto finta di niente\nMa ho capito, sì\nQuante volte sono arrivati i guai\nAnche se ero già migliore ormai\nIo non voglio più vivere\nSolo per fare compagnia\nIo non voglio più ridere\nNon mi diverto più ed è colpa mia\nNon ho voglia di credere\nChe domani sarà\nSarà diverso e poi si vedrà",
        "mp3FileName": "test.mp3"
    },{
        "name": "Quante volte",
        "lyrics": "Quante cose son cambiate nella vita\nQuante cose sono sempre così\nQuante volte ho pensato è finita\nPoi mi risvegliavo il lunedì\nQuante volte ho pensato nella vita\nVoglio fare quello che mi va\nPoi le cose mi sfuggivan tra le dita\nE arrivava la realtà\nQuante cose son passate ormai, eh\nQuante cose che non torneranno mai\nQuante volte ho pensato nella vita\nPosso fare anche senza di te\nPoi mi risvegliavo tutto sudato\nSenza capire perché\nQuante volte ho sbagliato, sì\nQuante volte è andata bene così\nQuante volte ho fatto finta di niente\nMa ho capito, sì\nQuante volte sono arrivati i guai\nAnche se ero già migliore ormai\nIo non voglio più vivere\nSolo per fare compagnia\nIo non voglio più ridere\nNon mi diverto più ed è colpa mia\nNon ho voglia di credere\nChe domani sarà\nSarà diverso e poi chi lo sa?\nQuante volte ho pensato nella vita\nPosso fare anche senza di te\nPoi mi risvegliavo tutto sudato\nSenza vita che è\nQuante volte ho sbagliato sì\nQuante volte è andata bene così, eeh\nQuante volte ho fatto finta di niente\nMa ho capito, sì\nQuante volte sono arrivati i guai\nAnche se ero già migliore ormai\nIo non voglio più vivere\nSolo per fare compagnia\nIo non voglio più ridere\nNon mi diverto più ed è colpa mia\nNon ho voglia di credere\nChe domani sarà\nSarà diverso e poi si vedrà",
        "mp3FileName": "test.mp3"
    }]
}